MANIFEST.in
README.txt
setup.cfg
setup.py
zopeskel.txt
docs/HISTORY.txt
docs/INSTALL.txt
docs/LICENSE.txt
plonetheme/__init__.py
plonetheme.level2.egg-info/PKG-INFO
plonetheme.level2.egg-info/SOURCES.txt
plonetheme.level2.egg-info/dependency_links.txt
plonetheme.level2.egg-info/entry_points.txt
plonetheme.level2.egg-info/namespace_packages.txt
plonetheme.level2.egg-info/not-zip-safe
plonetheme.level2.egg-info/paster_plugins.txt
plonetheme.level2.egg-info/requires.txt
plonetheme.level2.egg-info/top_level.txt
plonetheme/level2/__init__.py
plonetheme/level2/configure.zcml
plonetheme/level2/profiles.zcml
plonetheme/level2/setuphandlers.py
plonetheme/level2/skins.zcml
plonetheme/level2/tests.py
plonetheme/level2/version.txt
plonetheme/level2/browser/__init__.py
plonetheme/level2/browser/borderAboveContent.pt
plonetheme/level2/browser/borderAboveContent.pt~
plonetheme/level2/browser/borderBelowContent.pt
plonetheme/level2/browser/borderBelowContent.pt~
plonetheme/level2/browser/configure.zcml
plonetheme/level2/browser/configure.zcml~
plonetheme/level2/browser/interfaces.py
plonetheme/level2/browser/viewlet.pt
plonetheme/level2/browser/viewlets.py
plonetheme/level2/browser/images/README.txt
plonetheme/level2/browser/images/img01.gif
plonetheme/level2/browser/images/img02.gif
plonetheme/level2/browser/images/img03.gif
plonetheme/level2/browser/images/img04.gif
plonetheme/level2/browser/images/img05.gif
plonetheme/level2/browser/images/img06.gif
plonetheme/level2/browser/images/img07.gif
plonetheme/level2/browser/images/img08.gif
plonetheme/level2/browser/images/img09.gif
plonetheme/level2/browser/images/img10.gif
plonetheme/level2/browser/images/img13.gif
plonetheme/level2/browser/images/img14.gif
plonetheme/level2/browser/images/img15.gif
plonetheme/level2/browser/images/spacer.gif
plonetheme/level2/browser/stylesheets/README.txt
plonetheme/level2/browser/stylesheets/main.css
plonetheme/level2/browser/stylesheets/main.css~
plonetheme/level2/profiles/default/cssregistry.xml
plonetheme/level2/profiles/default/import_steps.xml
plonetheme/level2/profiles/default/jsregistry.xml
plonetheme/level2/profiles/default/metadata.xml
plonetheme/level2/profiles/default/plonetheme.level2_various.txt
plonetheme/level2/profiles/default/skins.xml
plonetheme/level2/profiles/default/viewlets.xml
plonetheme/level2/skins/plonetheme_level2_custom_images/CONTENT.txt
